star_local/__init__.py
star_local/exception_star.py
star_local/star_constants.py
star_local/star_local.py
star_local/star_transaction.py
star_local-0.0.20.dist-info/METADATA
star_local-0.0.20.dist-info/WHEEL
star_local-0.0.20.dist-info/top_level.txt
star_local-0.0.20.dist-info/RECORD
