Metadata-Version: 2.1
Name: star-local
Version: 0.0.20
Summary: PyPI Package for Circles star-local Python
Home-page: https://github.com/circles-zone/star-local-python-package
Author: Circles
Author-email: info@circlez.ai
Classifier: Programming Language :: Python :: 3
Classifier: License :: Other/Proprietary License
Classifier: Operating System :: OS Independent
Requires-Dist: database-mysql-local >=0.0.199
Requires-Dist: logger-local >=0.0.133
Requires-Dist: user-context-remote >=0.0.17
Requires-Dist: python-sdk-remote >=0.0.27
